{"cameraMode":{"drawMode":0,"name":"Shaded","section":"Shading Mode"},"sceneLighting":false,"audioPlay":false,"sceneViewState":{"showFog":true,"showMaterialUpdate":false,"showSkybox":false,"showFlares":true,"showImageEffects":true,"showParticleSystems":true},"in2DMode":false,"pivot":{"x":-3.702838897705078,"y":0.9582800269126892,"z":0.3421791195869446},"rotation":{"x":0.10058886557817459,"y":-0.08110782504081726,"z":0.008237768895924092,"w":0.9916016459465027},"size":1.1818127632141114,"orthographic":false}